allalgorithms/__init__.py
allalgorithms-0.0.0.dist-info/METADATA
allalgorithms-0.0.0.dist-info/RECORD
allalgorithms-0.0.0.dist-info/WHEEL
allalgorithms-0.0.0.dist-info/top_level.txt
