Metadata-Version: 2.1
Name: allalgorithms
Version: 0.0.0
Summary: All Algorithms in Python
Home-page: https://python.allalgorithms.com
Author: Carlos Abraham
Author-email: abraham@abranhe.com
License: MIT
Project-URL: Source, https://github.com/abranhe/python-lib
Platform: UNKNOWN
Classifier: Programming Language :: Python
Classifier: Intended Audience :: Developers
Classifier: License :: OSI Approved :: MIT License
Classifier: Programming Language :: Python :: 3
Classifier: Programming Language :: Python :: 3.2
Classifier: Programming Language :: Python :: 3.4
Classifier: Programming Language :: Python :: 3.5
Classifier: Programming Language :: Python :: 3.6
